.travis.yml
AUTHORS
ChangeLog
LICENSE
MANIFEST.in
README.rst
requirements-tests.txt
requirements.txt
setup.cfg
setup.py
tox.ini
otopimdp/__init__.py
otopimdp/constants.py
otopimdp/errors.py
otopimdp/parser.py
otopimdp/utils.py
python_otopi_mdp.egg-info/PKG-INFO
python_otopi_mdp.egg-info/SOURCES.txt
python_otopi_mdp.egg-info/dependency_links.txt
python_otopi_mdp.egg-info/not-zip-safe
python_otopi_mdp.egg-info/pbr.json
python_otopi_mdp.egg-info/requires.txt
python_otopi_mdp.egg-info/top_level.txt
tests/test_parser.py
tests/test_utils.py